spatialpandas/__init__.py
spatialpandas/__version.py
spatialpandas/_optional_imports.py
spatialpandas/_version.py
spatialpandas/dask.py
spatialpandas/geodataframe.py
spatialpandas/geoseries.py
spatialpandas/utils.py
spatialpandas/geometry/__init__.py
spatialpandas/geometry/base.py
spatialpandas/geometry/basefixed.py
spatialpandas/geometry/baselist.py
spatialpandas/geometry/line.py
spatialpandas/geometry/multiline.py
spatialpandas/geometry/multipoint.py
spatialpandas/geometry/multipolygon.py
spatialpandas/geometry/point.py
spatialpandas/geometry/polygon.py
spatialpandas/geometry/ring.py
spatialpandas/geometry/_algorithms/__init__.py
spatialpandas/geometry/_algorithms/bounds.py
spatialpandas/geometry/_algorithms/intersection.py
spatialpandas/geometry/_algorithms/measures.py
spatialpandas/geometry/_algorithms/orientation.py
spatialpandas/io/__init__.py
spatialpandas/io/parquet.py
spatialpandas/io/utils.py
spatialpandas/spatialindex/__init__.py
spatialpandas/spatialindex/hilbert_curve.py
spatialpandas/spatialindex/rtree.py
spatialpandas/tests/__init__.py
spatialpandas/tests/_create_testdata.py
spatialpandas/tests/test_dask_autoimport.py
spatialpandas/tests/test_fixedextensionarray.py
spatialpandas/tests/test_geodataframe.py
spatialpandas/tests/test_listextensionarray.py
spatialpandas/tests/test_parquet.py
spatialpandas/tests/test_parquet_s3.py
spatialpandas/tests/geometry/__init__.py
spatialpandas/tests/geometry/strategies.py
spatialpandas/tests/geometry/test_construction.py
spatialpandas/tests/geometry/test_cx.py
spatialpandas/tests/geometry/test_geometry.py
spatialpandas/tests/geometry/test_to_geopandas.py
spatialpandas/tests/geometry/algorithms/__init__.py
spatialpandas/tests/geometry/algorithms/test_intersection.py
spatialpandas/tests/geometry/algorithms/test_measures.py
spatialpandas/tests/geometry/algorithms/test_orientation.py
spatialpandas/tests/geometry/intersection/__init__.py
spatialpandas/tests/geometry/intersection/test_point_intersection.py
spatialpandas-0.5.0.dist-info/METADATA
spatialpandas-0.5.0.dist-info/WHEEL
spatialpandas-0.5.0.dist-info/licenses/LICENSE
spatialpandas-0.5.0.dist-info/licenses/NOTICE
spatialpandas-0.5.0.dist-info/RECORD
