Metadata-Version: 2.4
Name: spatialpandas
Version: 0.5.0
Summary: Pandas extension arrays for spatial/geometric operations
Project-URL: Homepage, https://github.com/holoviz/spatialpandas
Project-URL: Source, https://github.com/holoviz/spatialpandas
Project-URL: HoloViz, https://holoviz.org/
Author-email: HoloViz developers <developers@holoviz.org>
Maintainer-email: HoloViz developers <developers@holoviz.org>
License: BSD-2-Clause
License-File: LICENSE
License-File: NOTICE
Classifier: Development Status :: 5 - Production/Stable
Classifier: Intended Audience :: Developers
Classifier: Intended Audience :: Science/Research
Classifier: License :: OSI Approved :: BSD License
Classifier: Natural Language :: English
Classifier: Operating System :: OS Independent
Classifier: Programming Language :: Python :: 3
Classifier: Programming Language :: Python :: 3.10
Classifier: Programming Language :: Python :: 3.11
Classifier: Programming Language :: Python :: 3.12
Classifier: Programming Language :: Python :: 3.13
Classifier: Topic :: Scientific/Engineering
Classifier: Topic :: Software Development :: Libraries
Requires-Python: >=3.10
Requires-Dist: dask>=2025.1
Requires-Dist: fsspec>=2022.8
Requires-Dist: numba
Requires-Dist: packaging
Requires-Dist: pandas>=2.0
Requires-Dist: pyarrow>=14.0.1
Requires-Dist: retrying
Provides-Extra: tests
Requires-Dist: hypothesis; extra == 'tests'
Requires-Dist: pytest; extra == 'tests'
